{"response": {"version": "0.1", "termsofService": "http://www.wunderground.com/weather/api/d/terms.html", "features": {"history": 1}}, "history": {"date": {"pretty": "August 25, 2012", "year": "2012", "mon": "08", "mday": "25", "hour": "12", "min": "00", "tzname": "America/New_York"}, "utcdate": {"pretty": "August 25, 2012", "year": "2012", "mon": "08", "mday": "25", "hour": "16", "min": "00", "tzname": "UTC"}, "observations": [{"date": {"pretty": "12:54 AM EDT on August 25, 2012", "year": "2012", "mon": "08", "mday": "25", "hour": "00", "min": "54", "tzname": "America/New_York"}, "utcdate": {"pretty": "4:54 AM GMT on August 25, 2012", "year": "2012", "mon": "08", "mday": "25", "hour": "04", "min": "54", "tzname": "UTC"}, "tempm": "20.0", "tempi": "68.0", "dewptm": "18.3", "dewpti": "64.9", "hum": "90", "wspdm": "0.0", "wspdi": "0.0", "wgustm": "-9999.0", "wgusti": "-9999.0", "wdird": "0", "wdire": "North", "vism": "12.9", "visi": "8.0", "pressurem": "1023.3", "pressurei": "30.22", "windchillm": "-999", "windchilli": "-999", "heatindexm": "-9999", "heatindexi": "-9999", "precipm": "-9999.00", "precipi": "-9999.00", "conds": "Mostly Cloudy", "icon": "mostlycloudy", "fog": "0", "rain": "0", "snow": "0", "hail": "0", "thunder": "0", "tornado": "0", "metar": "METAR KBOS 250454Z 00000KT 8SM BKN090 20/18 A3022 RMK AO2 SLP233 T02000183 402560200"}, {"date": {"pretty": "1:54 AM EDT on August 25, 2012", "year": "2012", "mon": "08", "mday": "25", "hour": "01", "min": "54", "tzname": "America/New_York"}, "utcdate": {"pretty": "5:54 AM GMT on August 25, 2012", "year": "2012", "mon": "08", "mday": "25", "hour": "05", "min": "54", "tzname": "UTC"}, "tempm": "20.0", "tempi": "68.0", "dewptm": "18.3", "dewpti": "64.9", "hum": "90", "wspdm": "7.4", "wspdi": "4.6", "wgustm": "-9999.0", "wgusti": "-9999.0", "wdird": "80", "wdire": "East", "vism": "16.1", "visi": "10.0", "pressurem": "1023.5", "pressurei": "30.23", "windchillm": "-999", "windchilli": "-999", "heatindexm": "-9999", "heatindexi": "-9999", "precipm": "-9999.00", "precipi": "-9999.00", "conds": "Mostly Cloudy", "icon": "mostlycloudy", "fog": "0", "rain": "0", "snow": "0", "hail": "0", "thunder": "0", "tornado": "0", "metar": "METAR KBOS 250554Z 08004KT 10SM BKN120 20/18 A3023 RMK AO2 SLP235 T02000183 10211 20200 53004"}, {"date": {"pretty": "2:54 AM EDT on August 25, 2012", "year": "2012", "mon": "08", "mday": "25", "hour": "02", "min": "54", "tzname": "America/New_York"}, "utcdate": {"pretty": "6:54 AM GMT on August 25, 2012", "year": "2012", "mon": "08", "mday": "25", "hour": "06", "min": "54", "tzname": "UTC"}, "tempm": "20.0", "tempi": "68.0", "dewptm": "18.3", "dewpti": "64.9", "hum": "90", "wspdm": "5.6", "wspdi": "3.5", "wgustm": "-9999.0", "wgusti": "-9999.0", "wdird": "80", "wdire": "East", "vism": "14.5", "visi": "9.0", "pressurem": "1023.8", "pressurei": "30.24", "windchillm": "-999", "windchilli": "-999", "heatindexm": "-9999", "heatindexi": "-9999", "precipm": "-9999.00", "precipi": "-9999.00", "conds": "Mostly Cloudy", "icon": "mostlycloudy", "fog": "0", "rain": "0", "snow": "0", "hail": "0", "thunder": "0", "tornado": "0", "metar": "METAR KBOS 250654Z 08003KT 9SM BKN090 20/18 A3024 RMK AO2 SLP238 T02000183"}, {"date": {"pretty": "3:54 AM EDT on August 25, 2012", "year": "2012", "mon": "08", "mday": "25", "hour": "03", "min": "54", "tzname": "America/New_York"}, "utcdate": {"pretty": "7:54 AM GMT on August 25, 2012", "year": "2012", "mon": "08", "mday": "25", "hour": "07", "min": "54", "tzname": "UTC"}, "tempm": "20.0", "tempi": "68.0", "dewptm": "18.3", "dewpti": "64.9", "hum": "90", "wspdm": "7.4", "wspdi": "4.6", "wgustm": "-9999.0", "wgusti": "-9999.0", "wdird": "50", "wdire": "NE", "vism": "9.7", "visi": "6.0", "pressurem": "1024.0", "pressurei": "30.24", "windchillm": "-999", "windchilli": "-999", "heatindexm": "-9999", "heatindexi": "-9999", "precipm": "-9999.00", "precipi": "-9999.00", "conds": "Mostly Cloudy", "icon": "mostlycloudy", "fog": "0", "rain": "0", "snow": "0", "hail": "0", "thunder": "0", "tornado": "0", "metar": "METAR KBOS 250754Z 05004KT 6SM BR BKN090 20/18 A3024 RMK AO2 VIS 2 1/2 E SLP240 T02000183"}, {"date": {"pretty": "4:54 AM EDT on August 25, 2012", "year": "2012", "mon": "08", "mday": "25", "hour": "04", "min": "54", "tzname": "America/New_York"}, "utcdate": {"pretty": "8:54 AM GMT on August 25, 2012", "year": "2012", "mon": "08", "mday": "25", "hour": "08", "min": "54", "tzname": "UTC"}, "tempm": "20.0", "tempi": "68.0", "dewptm": "18.9", "dewpti": "66.0", "hum": "93", "wspdm": "0.0", "wspdi": "0.0", "wgustm": "-9999.0", "wgusti": "-9999.0", "wdird": "0", "wdire": "North", "vism": "4.8", "visi": "3.0", "pressurem": "1024.3", "pressurei": "30.25", "windchillm": "-999", "windchilli": "-999", "heatindexm": "-9999", "heatindexi": "-9999", "precipm": "-9999.00", "precipi": "-9999.00", "conds": "Mostly Cloudy", "icon": "mostlycloudy", "fog": "0", "rain": "0", "snow": "0", "hail": "0", "thunder": "0", "tornado": "0", "metar": "METAR KBOS 250854Z 00000KT 3SM BR BKN095 20/19 A3025 RMK AO2 VIS 2 E SLP243 T02000189 51009"}, {"date": {"pretty": "5:54 AM EDT on August 25, 2012", "year": "2012", "mon": "08", "mday": "25", "hour": "05", "min": "54", "tzname": "America/New_York"}, "utcdate": {"pretty": "9:54 AM GMT on August 25, 2012", "year": "2012", "mon": "08", "mday": "25", "hour": "09", "min": "54", "tzname": "UTC"}, "tempm": "20.0", "tempi": "68.0", "dewptm": "18.9", "dewpti": "66.0", "hum": "93", "wspdm": "0.0", "wspdi": "0.0", "wgustm": "-9999.0", "wgusti": "-9999.0", "wdird": "0", "wdire": "North", "vism": "6.4", "visi": "4.0", "pressurem": "1025.0", "pressurei": "30.27", "windchillm": "-999", "windchilli": "-999", "heatindexm": "-9999", "heatindexi": "-9999", "precipm": "-9999.00", "precipi": "-9999.00", "conds": "Overcast", "icon": "cloudy", "fog": "0", "rain": "0", "snow": "0", "hail": "0", "thunder": "0", "tornado": "0", "metar": "METAR KBOS 250954Z 00000KT 4SM BR FEW050 BKN060 OVC100 20/19 A3027 RMK AO2 SLP250 T02000189"}, {"date": {"pretty": "6:54 AM EDT on August 25, 2012", "year": "2012", "mon": "08", "mday": "25", "hour": "06", "min": "54", "tzname": "America/New_York"}, "utcdate": {"pretty": "10:54 AM GMT on August 25, 2012", "year": "2012", "mon": "08", "mday": "25", "hour": "10", "min": "54", "tzname": "UTC"}, "tempm": "20.0", "tempi": "68.0", "dewptm": "18.9", "dewpti": "66.0", "hum": "93", "wspdm": "5.6", "wspdi": "3.5", "wgustm": "-9999.0", "wgusti": "-9999.0", "wdird": "80", "wdire": "East", "vism": "4.8", "visi": "3.0", "pressurem": "1025.4", "pressurei": "30.28", "windchillm": "-999", "windchilli": "-999", "heatindexm": "-9999", "heatindexi": "-9999", "precipm": "-9999.00", "precipi": "-9999.00", "conds": "Overcast", "icon": "cloudy", "fog": "0", "rain": "0", "snow": "0", "hail": "0", "thunder": "0", "tornado": "0", "metar": "METAR KBOS 251054Z 08003KT 3SM BR FEW045 SCT060 BKN100 OVC280 20/19 A3028 RMK AO2 SLP254 T02000189"}, {"date": {"pretty": "7:47 AM EDT on August 25, 2012", "year": "2012", "mon": "08", "mday": "25", "hour": "07", "min": "47", "tzname": "America/New_York"}, "utcdate": {"pretty": "11:47 AM GMT on August 25, 2012", "year": "2012", "mon": "08", "mday": "25", "hour": "11", "min": "47", "tzname": "UTC"}, "tempm": "21.0", "tempi": "69.8", "dewptm": "19.0", "dewpti": "66.2", "hum": "88", "wspdm": "0.0", "wspdi": "0.0", "wgustm": "-9999.0", "wgusti": "-9999.0", "wdird": "0", "wdire": "North", "vism": "8.0", "visi": "5.0", "pressurem": "1026.0", "pressurei": "30.30", "windchillm": "-999", "windchilli": "-999", "heatindexm": "-9999", "heatindexi": "-9999", "precipm": "-9999.00", "precipi": "-9999.00", "conds": "Overcast", "icon": "cloudy", "fog": "0", "rain": "0", "snow": "0", "hail": "0", "thunder": "0", "tornado": "0", "metar": "SPECI KBOS 251147Z 00000KT 5SM BR FEW003 BKN055 BKN080 OVC280 21/19 A3030 RMK AO2"}, {"date": {"pretty": "7:54 AM EDT on August 25, 2012", "year": "2012", "mon": "08", "mday": "25", "hour": "07", "min": "54", "tzname": "America/New_York"}, "utcdate": {"pretty": "11:54 AM GMT on August 25, 2012", "year": "2012", "mon": "08", "mday": "25", "hour": "11", "min": "54", "tzname": "UTC"}, "tempm": "20.6", "tempi": "69.1", "dewptm": "18.9", "dewpti": "66.0", "hum": "90", "wspdm": "9.3", "wspdi": "5.8", "wgustm": "-9999.0", "wgusti": "-9999.0", "wdird": "70", "wdire": "ENE", "vism": "8.0", "visi": "5.0", "pressurem": "1026.1", "pressurei": "30.30", "windchillm": "-999", "windchilli": "-999", "heatindexm": "-9999", "heatindexi": "-9999", "precipm": "-9999.00", "precipi": "-9999.00", "conds": "Overcast", "icon": "cloudy", "fog": "0", "rain": "0", "snow": "0", "hail": "0", "thunder": "0", "tornado": "0", "metar": "METAR KBOS 251154Z 07005KT 5SM BR FEW003 BKN055 BKN080 OVC280 21/19 A3030 RMK AO2 SLP261 T02060189 10206 20194 52018"}, {"date": {"pretty": "8:54 AM EDT on August 25, 2012", "year": "2012", "mon": "08", "mday": "25", "hour": "08", "min": "54", "tzname": "America/New_York"}, "utcdate": {"pretty": "12:54 PM GMT on August 25, 2012", "year": "2012", "mon": "08", "mday": "25", "hour": "12", "min": "54", "tzname": "UTC"}, "tempm": "21.1", "tempi": "70.0", "dewptm": "19.4", "dewpti": "66.9", "hum": "90", "wspdm": "7.4", "wspdi": "4.6", "wgustm": "-9999.0", "wgusti": "-9999.0", "wdird": "60", "wdire": "ENE", "vism": "11.3", "visi": "7.0", "pressurem": "1026.3", "pressurei": "30.31", "windchillm": "-999", "windchilli": "-999", "heatindexm": "-9999", "heatindexi": "-9999", "precipm": "-9999.00", "precipi": "-9999.00", "conds": "Overcast", "icon": "cloudy", "fog": "0", "rain": "0", "snow": "0", "hail": "0", "thunder": "0", "tornado": "0", "metar": "METAR KBOS 251254Z 06004KT 7SM FEW003 SCT055 SCT080 OVC280 21/19 A3031 RMK AO2 SLP263 VIS LWR E T02110194"}, {"date": {"pretty": "9:54 AM EDT on August 25, 2012", "year": "2012", "mon": "08", "mday": "25", "hour": "09", "min": "54", "tzname": "America/New_York"}, "utcdate": {"pretty": "1:54 PM GMT on August 25, 2012", "year": "2012", "mon": "08", "mday": "25", "hour": "13", "min": "54", "tzname": "UTC"}, "tempm": "22.2", "tempi": "72.0", "dewptm": "19.4", "dewpti": "66.9", "hum": "84", "wspdm": "9.3", "wspdi": "5.8", "wgustm": "-9999.0", "wgusti": "-9999.0", "wdird": "70", "wdire": "ENE", "vism": "12.9", "visi": "8.0", "pressurem": "1026.8", "pressurei": "30.32", "windchillm": "-999", "windchilli": "-999", "heatindexm": "-9999", "heatindexi": "-9999", "precipm": "-9999.00", "precipi": "-9999.00", "conds": "Overcast", "icon": "cloudy", "fog": "0", "rain": "0", "snow": "0", "hail": "0", "thunder": "0", "tornado": "0", "metar": "METAR KBOS 251354Z 07005KT 8SM FEW007 SCT065 OVC280 22/19 A3032 RMK AO2 SLP268 VIS LWR E-S T02220194"}, {"date": {"pretty": "10:54 AM EDT on August 25, 2012", "year": "2012", "mon": "08", "mday": "25", "hour": "10", "min": "54", "tzname": "America/New_York"}, "utcdate": {"pretty": "2:54 PM GMT on August 25, 2012", "year": "2012", "mon": "08", "mday": "25", "hour": "14", "min": "54", "tzname": "UTC"}, "tempm": "22.8", "tempi": "73.0", "dewptm": "18.9", "dewpti": "66.0", "hum": "79", "wspdm": "13.0", "wspdi": "8.1", "wgustm": "-9999.0", "wgusti": "-9999.0", "wdird": "70", "wdire": "ENE", "vism": "16.1", "visi": "10.0", "pressurem": "1027.1", "pressurei": "30.33", "windchillm": "-999", "windchilli": "-999", "heatindexm": "-9999", "heatindexi": "-9999", "precipm": "-9999.00", "precipi": "-9999.00", "conds": "Overcast", "icon": "cloudy", "fog": "0", "rain": "0", "snow": "0", "hail": "0", "thunder": "0", "tornado": "0", "metar": "METAR KBOS 251454Z 07007KT 10SM FEW018 SCT060 BKN200 OVC250 23/19 A3033 RMK AO2 SLP271 T02280189 53009"}, {"date": {"pretty": "11:54 AM EDT on August 25, 2012", "year": "2012", "mon": "08", "mday": "25", "hour": "11", "min": "54", "tzname": "America/New_York"}, "utcdate": {"pretty": "3:54 PM GMT on August 25, 2012", "year": "2012", "mon": "08", "mday": "25", "hour": "15", "min": "54", "tzname": "UTC"}, "tempm": "23.9", "tempi": "75.0", "dewptm": "19.4", "dewpti": "66.9", "hum": "76", "wspdm": "13.0", "wspdi": "8.1", "wgustm": "-9999.0", "wgusti": "-9999.0", "wdird": "80", "wdire": "East", "vism": "16.1", "visi": "10.0", "pressurem": "1026.9", "pressurei": "30.33", "windchillm": "-999", "windchilli": "-999", "heatindexm": "-9999", "heatindexi": "-9999", "precipm": "-9999.00", "precipi": "-9999.00", "conds": "Overcast", "icon": "cloudy", "fog": "0", "rain": "0", "snow": "0", "hail": "0", "thunder": "0", "tornado": "0", "metar": "METAR KBOS 251554Z 08007KT 10SM FEW016 SCT070 OVC250 24/19 A3033 RMK AO2 SLP269 T02390194"}, {"date": {"pretty": "12:54 PM EDT on August 25, 2012", "year": "2012", "mon": "08", "mday": "25", "hour": "12", "min": "54", "tzname": "America/New_York"}, "utcdate": {"pretty": "4:54 PM GMT on August 25, 2012", "year": "2012", "mon": "08", "mday": "25", "hour": "16", "min": "54", "tzname": "UTC"}, "tempm": "23.9", "tempi": "75.0", "dewptm": "16.7", "dewpti": "62.1", "hum": "64", "wspdm": "20.4", "wspdi": "12.7", "wgustm": "-9999.0", "wgusti": "-9999.0", "wdird": "100", "wdire": "East", "vism": "16.1", "visi": "10.0", "pressurem": "1026.5", "pressurei": "30.32", "windchillm": "-999", "windchilli": "-999", "heatindexm": "-9999", "heatindexi": "-9999", "precipm": "-9999.00", "precipi": "-9999.00", "conds": "Overcast", "icon": "cloudy", "fog": "0", "rain": "0", "snow": "0", "hail": "0", "thunder": "0", "tornado": "0", "metar": "METAR KBOS 251654Z 10011KT 10SM FEW025 OVC300 24/17 A3032 RMK AO2 SLP265 T02390167"}, {"date": {"pretty": "1:54 PM EDT on August 25, 2012", "year": "2012", "mon": "08", "mday": "25", "hour": "13", "min": "54", "tzname": "America/New_York"}, "utcdate": {"pretty": "5:54 PM GMT on August 25, 2012", "year": "2012", "mon": "08", "mday": "25", "hour": "17", "min": "54", "tzname": "UTC"}, "tempm": "24.4", "tempi": "75.9", "dewptm": "16.1", "dewpti": "61.0", "hum": "60", "wspdm": "18.5", "wspdi": "11.5", "wgustm": "-9999.0", "wgusti": "-9999.0", "wdird": "90", "wdire": "East", "vism": "16.1", "visi": "10.0", "pressurem": "1026.2", "pressurei": "30.31", "windchillm": "-999", "windchilli": "-999", "heatindexm": "-9999", "heatindexi": "-9999", "precipm": "-9999.00", "precipi": "-9999.00", "conds": "Mostly Cloudy", "icon": "mostlycloudy", "fog": "0", "rain": "0", "snow": "0", "hail": "0", "thunder": "0", "tornado": "0", "metar": "METAR KBOS 251754Z 09010KT 10SM FEW035 SCT220 BKN300 24/16 A3031 RMK AO2 SLP262 T02440161 10250 20200 58008"}, {"date": {"pretty": "2:54 PM EDT on August 25, 2012", "year": "2012", "mon": "08", "mday": "25", "hour": "14", "min": "54", "tzname": "America/New_York"}, "utcdate": {"pretty": "6:54 PM GMT on August 25, 2012", "year": "2012", "mon": "08", "mday": "25", "hour": "18", "min": "54", "tzname": "UTC"}, "tempm": "23.3", "tempi": "73.9", "dewptm": "16.1", "dewpti": "61.0", "hum": "64", "wspdm": "20.4", "wspdi": "12.7", "wgustm": "-9999.0", "wgusti": "-9999.0", "wdird": "100", "wdire": "East", "vism": "16.1", "visi": "10.0", "pressurem": "1026.1", "pressurei": "30.30", "windchillm": "-999", "windchilli": "-999", "heatindexm": "-9999", "heatindexi": "-9999", "precipm": "-9999.00", "precipi": "-9999.00", "conds": "Mostly Cloudy", "icon": "mostlycloudy", "fog": "0", "rain": "0", "snow": "0", "hail": "0", "thunder": "0", "tornado": "0", "metar": "METAR KBOS 251854Z 10011KT 10SM FEW040 SCT100 SCT220 BKN300 23/16 A3030 RMK AO2 SLP261 T02330161"}, {"date": {"pretty": "3:54 PM EDT on August 25, 2012", "year": "2012", "mon": "08", "mday": "25", "hour": "15", "min": "54", "tzname": "America/New_York"}, "utcdate": {"pretty": "7:54 PM GMT on August 25, 2012", "year": "2012", "mon": "08", "mday": "25", "hour": "19", "min": "54", "tzname": "UTC"}, "tempm": "22.8", "tempi": "73.0", "dewptm": "16.7", "dewpti": "62.1", "hum": "68", "wspdm": "14.8", "wspdi": "9.2", "wgustm": "-9999.0", "wgusti": "-9999.0", "wdird": "110", "wdire": "ESE", "vism": "16.1", "visi": "10.0", "pressurem": "1026.2", "pressurei": "30.31", "windchillm": "-999", "windchilli": "-999", "heatindexm": "-9999", "heatindexi": "-9999", "precipm": "-9999.00", "precipi": "-9999.00", "conds": "Mostly Cloudy", "icon": "mostlycloudy", "fog": "0", "rain": "0", "snow": "0", "hail": "0", "thunder": "0", "tornado": "0", "metar": "METAR KBOS 251954Z 11008KT 10SM FEW050 SCT220 BKN300 23/17 A3031 RMK AO2 SLP262 T02280167"}, {"date": {"pretty": "4:54 PM EDT on August 25, 2012", "year": "2012", "mon": "08", "mday": "25", "hour": "16", "min": "54", "tzname": "America/New_York"}, "utcdate": {"pretty": "8:54 PM GMT on August 25, 2012", "year": "2012", "mon": "08", "mday": "25", "hour": "20", "min": "54", "tzname": "UTC"}, "tempm": "23.3", "tempi": "73.9", "dewptm": "15.0", "dewpti": "59.0", "hum": "59", "wspdm": "20.4", "wspdi": "12.7", "wgustm": "-9999.0", "wgusti": "-9999.0", "wdird": "110", "wdire": "ESE", "vism": "16.1", "visi": "10.0", "pressurem": "1026.2", "pressurei": "30.31", "windchillm": "-999", "windchilli": "-999", "heatindexm": "-9999", "heatindexi": "-9999", "precipm": "-9999.00", "precipi": "-9999.00", "conds": "Mostly Cloudy", "icon": "mostlycloudy", "fog": "0", "rain": "0", "snow": "0", "hail": "0", "thunder": "0", "tornado": "0", "metar": "METAR KBOS 252054Z 11011KT 10SM FEW055 SCT220 BKN300 23/15 A3031 RMK AO2 SLP262 T02330150 55000"}, {"date": {"pretty": "5:54 PM EDT on August 25, 2012", "year": "2012", "mon": "08", "mday": "25", "hour": "17", "min": "54", "tzname": "America/New_York"}, "utcdate": {"pretty": "9:54 PM GMT on August 25, 2012", "year": "2012", "mon": "08", "mday": "25", "hour": "21", "min": "54", "tzname": "UTC"}, "tempm": "22.8", "tempi": "73.0", "dewptm": "16.7", "dewpti": "62.1", "hum": "68", "wspdm": "22.2", "wspdi": "13.8", "wgustm": "-9999.0", "wgusti": "-9999.0", "wdird": "110", "wdire": "ESE", "vism": "16.1", "visi": "10.0", "pressurem": "1026.3", "pressurei": "30.31", "windchillm": "-999", "windchilli": "-999", "heatindexm": "-9999", "heatindexi": "-9999", "precipm": "-9999.00", "precipi": "-9999.00", "conds": "Mostly Cloudy", "icon": "mostlycloudy", "fog": "0", "rain": "0", "snow": "0", "hail": "0", "thunder": "0", "tornado": "0", "metar": "METAR KBOS 252154Z 11012KT 10SM FEW220 BKN300 23/17 A3031 RMK AO2 SLP263 T02280167"}, {"date": {"pretty": "6:54 PM EDT on August 25, 2012", "year": "2012", "mon": "08", "mday": "25", "hour": "18", "min": "54", "tzname": "America/New_York"}, "utcdate": {"pretty": "10:54 PM GMT on August 25, 2012", "year": "2012", "mon": "08", "mday": "25", "hour": "22", "min": "54", "tzname": "UTC"}, "tempm": "21.7", "tempi": "71.1", "dewptm": "15.6", "dewpti": "60.1", "hum": "68", "wspdm": "14.8", "wspdi": "9.2", "wgustm": "-9999.0", "wgusti": "-9999.0", "wdird": "110", "wdire": "ESE", "vism": "16.1", "visi": "10.0", "pressurem": "1026.5", "pressurei": "30.32", "windchillm": "-999", "windchilli": "-999", "heatindexm": "-9999", "heatindexi": "-9999", "precipm": "-9999.00", "precipi": "-9999.00", "conds": "Scattered Clouds", "icon": "partlycloudy", "fog": "0", "rain": "0", "snow": "0", "hail": "0", "thunder": "0", "tornado": "0", "metar": "METAR KBOS 252254Z 11008KT 10SM FEW220 SCT300 22/16 A3032 RMK AO2 SLP265 T02170156"}, {"date": {"pretty": "7:54 PM EDT on August 25, 2012", "year": "2012", "mon": "08", "mday": "25", "hour": "19", "min": "54", "tzname": "America/New_York"}, "utcdate": {"pretty": "11:54 PM GMT on August 25, 2012", "year": "2012", "mon": "08", "mday": "25", "hour": "23", "min": "54", "tzname": "UTC"}, "tempm": "21.1", "tempi": "70.0", "dewptm": "15.6", "dewpti": "60.1", "hum": "71", "wspdm": "13.0", "wspdi": "8.1", "wgustm": "-9999.0", "wgusti": "-9999.0", "wdird": "120", "wdire": "ESE", "vism": "16.1", "visi": "10.0", "pressurem": "1026.8", "pressurei": "30.32", "windchillm": "-999", "windchilli": "-999", "heatindexm": "-9999", "heatindexi": "-9999", "precipm": "-9999.00", "precipi": "-9999.00", "conds": "Scattered Clouds", "icon": "partlycloudy", "fog": "0", "rain": "0", "snow": "0", "hail": "0", "thunder": "0", "tornado": "0", "metar": "METAR KBOS 252354Z 12007KT 10SM FEW200 SCT300 21/16 A3032 RMK AO2 SLP268 T02110156 10250 20206 53006"}, {"date": {"pretty": "8:54 PM EDT on August 25, 2012", "year": "2012", "mon": "08", "mday": "25", "hour": "20", "min": "54", "tzname": "America/New_York"}, "utcdate": {"pretty": "12:54 AM GMT on August 26, 2012", "year": "2012", "mon": "08", "mday": "26", "hour": "00", "min": "54", "tzname": "UTC"}, "tempm": "20.0", "tempi": "68.0", "dewptm": "17.2", "dewpti": "63.0", "hum": "84", "wspdm": "9.3", "wspdi": "5.8", "wgustm": "-9999.0", "wgusti": "-9999.0", "wdird": "120", "wdire": "ESE", "vism": "16.1", "visi": "10.0", "pressurem": "1027.2", "pressurei": "30.34", "windchillm": "-999", "windchilli": "-999", "heatindexm": "-9999", "heatindexi": "-9999", "precipm": "-9999.00", "precipi": "-9999.00", "conds": "Scattered Clouds", "icon": "partlycloudy", "fog": "0", "rain": "0", "snow": "0", "hail": "0", "thunder": "0", "tornado": "0", "metar": "METAR KBOS 260054Z 12005KT 10SM SCT300 20/17 A3034 RMK AO2 SLP272 T02000172"}, {"date": {"pretty": "9:54 PM EDT on August 25, 2012", "year": "2012", "mon": "08", "mday": "25", "hour": "21", "min": "54", "tzname": "America/New_York"}, "utcdate": {"pretty": "1:54 AM GMT on August 26, 2012", "year": "2012", "mon": "08", "mday": "26", "hour": "01", "min": "54", "tzname": "UTC"}, "tempm": "20.0", "tempi": "68.0", "dewptm": "17.2", "dewpti": "63.0", "hum": "84", "wspdm": "9.3", "wspdi": "5.8", "wgustm": "-9999.0", "wgusti": "-9999.0", "wdird": "110", "wdire": "ESE", "vism": "16.1", "visi": "10.0", "pressurem": "1027.0", "pressurei": "30.33", "windchillm": "-999", "windchilli": "-999", "heatindexm": "-9999", "heatindexi": "-9999", "precipm": "-9999.00", "precipi": "-9999.00", "conds": "Mostly Cloudy", "icon": "mostlycloudy", "fog": "0", "rain": "0", "snow": "0", "hail": "0", "thunder": "0", "tornado": "0", "metar": "METAR KBOS 260154Z 11005KT 10SM FEW180 BKN250 20/17 A3033 RMK AO2 SLP270 T02000172"}, {"date": {"pretty": "10:54 PM EDT on August 25, 2012", "year": "2012", "mon": "08", "mday": "25", "hour": "22", "min": "54", "tzname": "America/New_York"}, "utcdate": {"pretty": "2:54 AM GMT on August 26, 2012", "year": "2012", "mon": "08", "mday": "26", "hour": "02", "min": "54", "tzname": "UTC"}, "tempm": "20.0", "tempi": "68.0", "dewptm": "17.2", "dewpti": "63.0", "hum": "84", "wspdm": "9.3", "wspdi": "5.8", "wgustm": "-9999.0", "wgusti": "-9999.0", "wdird": "130", "wdire": "SE", "vism": "16.1", "visi": "10.0", "pressurem": "1026.8", "pressurei": "30.32", "windchillm": "-999", "windchilli": "-999", "heatindexm": "-9999", "heatindexi": "-9999", "precipm": "-9999.00", "precipi": "-9999.00", "conds": "Mostly Cloudy", "icon": "mostlycloudy", "fog": "0", "rain": "0", "snow": "0", "hail": "0", "thunder": "0", "tornado": "0", "metar": "METAR KBOS 260254Z 13005KT 10SM BKN250 20/17 A3032 RMK AO2 SLP268 T02000172 50000"}, {"date": {"pretty": "11:54 PM EDT on August 25, 2012", "year": "2012", "mon": "08", "mday": "25", "hour": "23", "min": "54", "tzname": "America/New_York"}, "utcdate": {"pretty": "3:54 AM GMT on August 26, 2012", "year": "2012", "mon": "08", "mday": "26", "hour": "03", "min": "54", "tzname": "UTC"}, "tempm": "19.4", "tempi": "66.9", "dewptm": "17.2", "dewpti": "63.0", "hum": "87", "wspdm": "5.6", "wspdi": "3.5", "wgustm": "-9999.0", "wgusti": "-9999.0", "wdird": "140", "wdire": "SE", "vism": "16.1", "visi": "10.0", "pressurem": "1026.7", "pressurei": "30.32", "windchillm": "-999", "windchilli": "-999", "heatindexm": "-9999", "heatindexi": "-9999", "precipm": "-9999.00", "precipi": "-9999.00", "conds": "Scattered Clouds", "icon": "partlycloudy", "fog": "0", "rain": "0", "snow": "0", "hail": "0", "thunder": "0", "tornado": "0", "metar": "METAR KBOS 260354Z 14003KT 10SM FEW150 SCT250 19/17 A3032 RMK AO2 SLP267 T01940172"}], "dailysummary": [{"date": {"pretty": "12:00 PM EDT on August 25, 2012", "year": "2012", "mon": "08", "mday": "25", "hour": "12", "min": "00", "tzname": "America/New_York"}, "fog": "0", "rain": "0", "snow": "0", "snowfallm": "0.00", "snowfalli": "0.00", "monthtodatesnowfallm": "0.00", "monthtodatesnowfalli": "0.00", "since1julsnowfallm": "0.00", "since1julsnowfalli": "0.00", "snowdepthm": "0.00", "snowdepthi": "0.00", "hail": "0", "thunder": "0", "tornado": "0", "meantempm": "22", "meantempi": "72", "meandewptm": "18", "meandewpti": "64", "meanpressurem": "1026", "meanpressurei": "30.30", "meanwindspdm": "11", "meanwindspdi": "7", "meanwdire": "", "meanwdird": "95", "meanvism": "14", "meanvisi": "8", "humidity": "", "maxtempm": "25", "maxtempi": "77", "mintempm": "19", "mintempi": "66", "maxhumidity": "93", "minhumidity": "60", "maxdewptm": "19", "maxdewpti": "67", "mindewptm": "15", "mindewpti": "59", "maxpressurem": "1027", "maxpressurei": "30.34", "minpressurem": "1023", "minpressurei": "30.22", "maxwspdm": "24", "maxwspdi": "15", "minwspdm": "0", "minwspdi": "0", "maxvism": "16", "maxvisi": "10", "minvism": "5", "minvisi": "3", "gdegreedays": "22", "heatingdegreedays": "0", "coolingdegreedays": "7", "precipm": "0.00", "precipi": "0.00", "precipsource": "", "heatingdegreedaysnormal": "0", "monthtodateheatingdegreedays": "0", "monthtodateheatingdegreedaysnormal": "0", "since1sepheatingdegreedays": "", "since1sepheatingdegreedaysnormal": "", "since1julheatingdegreedays": "0", "since1julheatingdegreedaysnormal": "6", "coolingdegreedaysnormal": "6", "monthtodatecoolingdegreedays": "253", "monthtodatecoolingdegreedaysnormal": "193", "since1sepcoolingdegreedays": "", "since1sepcoolingdegreedaysnormal": "", "since1jancoolingdegreedays": "776", "since1jancoolingdegreedaysnormal": "625"}]}}